zotomatic/__init__.py
zotomatic/api.py
zotomatic/cli.py
zotomatic/config.py
zotomatic/errors.py
zotomatic/i18n.py
zotomatic/logging.py
zotomatic/pipelines.py
zotomatic/db/schema.sql
zotomatic/db/migrations/001_init.sql
zotomatic/llm/__init__.py
zotomatic/llm/client.py
zotomatic/llm/prompts.py
zotomatic/llm/types.py
zotomatic/note/__init__.py
zotomatic/note/builder.py
zotomatic/note/types.py
zotomatic/note/updater.py
zotomatic/note/workflow.py
zotomatic/repositories/__init__.py
zotomatic/repositories/note_repository.py
zotomatic/repositories/pdf_repository.py
zotomatic/repositories/sqlite_base.py
zotomatic/repositories/types.py
zotomatic/repositories/llm_usage/__init__.py
zotomatic/repositories/llm_usage/repository.py
zotomatic/repositories/llm_usage/sqlite/__init__.py
zotomatic/repositories/llm_usage/sqlite/repository.py
zotomatic/repositories/llm_usage/sqlite/usage.py
zotomatic/repositories/watcher_state/__init__.py
zotomatic/repositories/watcher_state/repository.py
zotomatic/repositories/watcher_state/sqlite/__init__.py
zotomatic/repositories/watcher_state/sqlite/directory_state.py
zotomatic/repositories/watcher_state/sqlite/file_state.py
zotomatic/repositories/watcher_state/sqlite/meta.py
zotomatic/repositories/watcher_state/sqlite/pending.py
zotomatic/repositories/watcher_state/sqlite/repository.py
zotomatic/repositories/watcher_state/sqlite/zotero_attachment.py
zotomatic/services/__init__.py
zotomatic/services/llm_usage.py
zotomatic/services/pending_queue.py
zotomatic/services/pending_queue_processor.py
zotomatic/services/types.py
zotomatic/services/zotero_resolver.py
zotomatic/templates/note.md
zotomatic/utils/note.py
zotomatic/utils/pdf.py
zotomatic/utils/slug.py
zotomatic/watcher/__init__.py
zotomatic/watcher/types.py
zotomatic/watcher/watcher.py
zotomatic/zotero/__init__.py
zotomatic/zotero/client.py
zotomatic/zotero/enricher.py
zotomatic/zotero/formatters.py
zotomatic/zotero/mapper.py
zotomatic/zotero/types.py
zotomatic-0.1.1.dist-info/METADATA
zotomatic-0.1.1.dist-info/WHEEL
zotomatic-0.1.1.dist-info/entry_points.txt
zotomatic-0.1.1.dist-info/licenses/LICENSE
zotomatic-0.1.1.dist-info/RECORD
