Metadata-Version: 2.4
Name: zotomatic
Version: 0.1.1
Summary: A CLI tool for generating Markdown notes from academic PDF papers using customizable templates, Zotero metadata, and LLM-powered summaries.
Project-URL: Source, https://github.com/glyphcat/zotomatic
Project-URL: Issues, https://github.com/glyphcat/zotomatic/issues
Project-URL: Documentation, https://github.com/glyphcat/zotomatic/tree/main/docs
Author: glyphcat
License: MIT License
License-File: LICENSE
Keywords: academic,cli,llm,markdown,metadata,note,paper,pdf,research,summarization,tagging,template,zotero
Classifier: Development Status :: 3 - Alpha
Classifier: License :: OSI Approved :: MIT License
Classifier: Programming Language :: Python :: 3 :: Only
Classifier: Programming Language :: Python :: 3.10
Classifier: Programming Language :: Python :: 3.11
Classifier: Programming Language :: Python :: 3.12
Classifier: Programming Language :: Python :: 3.13
Requires-Python: >=3.10
Requires-Dist: httpx>=0.28.1
Requires-Dist: pdfminer-six>=20240706
Requires-Dist: pymupdf>=1.26.7
Requires-Dist: pyzotero>=1.6.16
Requires-Dist: watchfiles>=1.1.0
